chimerapy/orchestrator/__init__.py
chimerapy/orchestrator/dashboard_app.py
chimerapy/orchestrator/init_services.py
chimerapy/orchestrator/monads.py
chimerapy/orchestrator/orchestrator_config.py
chimerapy/orchestrator/utils.py
chimerapy/orchestrator/build/ChimeraPy.png
chimerapy/orchestrator/build/favicon.png
chimerapy/orchestrator/build/index.html
chimerapy/orchestrator/build/pipeline-design.html
chimerapy/orchestrator/build/_app/version.json
chimerapy/orchestrator/build/mocks/networkMap.json
chimerapy/orchestrator/cli/__init__.py
chimerapy/orchestrator/cli/__main__.py
chimerapy/orchestrator/models/__init__.py
chimerapy/orchestrator/models/cluster_models.py
chimerapy/orchestrator/models/pipeline_config.py
chimerapy/orchestrator/models/pipeline_models.py
chimerapy/orchestrator/models/registry_models.py
chimerapy/orchestrator/registered_nodes/__init__.py
chimerapy/orchestrator/registered_nodes/nodes.py
chimerapy/orchestrator/registry/__init__.py
chimerapy/orchestrator/registry/utils.py
chimerapy/orchestrator/routers/__init__.py
chimerapy/orchestrator/routers/cluster_router.py
chimerapy/orchestrator/routers/error_mappers.py
chimerapy/orchestrator/routers/pipeline_router.py
chimerapy/orchestrator/services/__init__.py
chimerapy/orchestrator/services/cluster_service/__init__.py
chimerapy/orchestrator/services/cluster_service/cluster_manager.py
chimerapy/orchestrator/services/cluster_service/states.json
chimerapy/orchestrator/services/cluster_service/updates_broadcaster.py
chimerapy/orchestrator/services/pipeline_service/__init__.py
chimerapy/orchestrator/services/pipeline_service/pipeline.py
chimerapy/orchestrator/services/pipeline_service/pipelines.py
chimerapy/orchestrator/state_machine/__init__.py
chimerapy/orchestrator/state_machine/exceptions.py
chimerapy/orchestrator/state_machine/fsm.py
chimerapy/orchestrator/state_machine/models.py
chimerapy/orchestrator/tests/__init__.py
chimerapy/orchestrator/tests/base_test.py
chimerapy/orchestrator/tests/test_monads.py
chimerapy_orchestrator-0.0.2.dist-info/LICENSE
chimerapy_orchestrator-0.0.2.dist-info/METADATA
chimerapy_orchestrator-0.0.2.dist-info/WHEEL
chimerapy_orchestrator-0.0.2.dist-info/entry_points.txt
chimerapy_orchestrator-0.0.2.dist-info/top_level.txt
chimerapy_orchestrator-0.0.2.dist-info/RECORD
