Metadata-Version: 2.1
Name: chimerapy-orchestrator
Version: 0.0.2
Summary: ChimeraPyOrchestrator: A webapp and CLI tool for orchestrating ChimeraPy pipelines
Author-email: Eduardo Davalos <eduardo.davalos.anaya@vanderbilt.edu>, Umesh Timalsina <umesh.timalsina@vanderbilt.edu>
License: GNU GENERAL PUBLIC LICENSE
Project-URL: homepath, https://github.com/chimerapy/Orchestrator
Project-URL: documentation, https://github.com/chimerapy/Orchestrator
Project-URL: repository, https://github.com/chimerapy/Orchestrator
Keywords: multimodal,data,distributed,streaming,real-time
Classifier: Programming Language :: Python :: 3
Classifier: Development Status :: 3 - Alpha
Classifier: Intended Audience :: Education
Classifier: Intended Audience :: Science/Research
Classifier: Topic :: Scientific/Engineering
Classifier: Topic :: Software Development
Classifier: Topic :: Software Development :: Libraries
Classifier: Topic :: Software Development :: Libraries :: Python Modules
Requires-Python: >3.6
License-File: LICENSE
Requires-Dist: chimerapy-engine
Requires-Dist: pydantic (>=2.0.0)
Requires-Dist: pydantic-settings
Requires-Dist: fastapi[all]
Requires-Dist: importlib-metadata
Provides-Extra: test
Requires-Dist: pytest ; extra == 'test'
Requires-Dist: pytest-anyio ; extra == 'test'
Requires-Dist: coveralls ; extra == 'test'
Requires-Dist: pre-commit ; extra == 'test'
Requires-Dist: coverage[toml] ; extra == 'test'
Requires-Dist: bump2version ; extra == 'test'
